{"word": "commit", "accent": "/k\u0259\u02c8m\u026at/", "mean_cn": "v.\u627f\u8bfa\uff0c\u4fdd\u8bc1\uff1b\u5e72\uff08\u574f\u4e8b\uff09", "mean_en": "to do something wrong or illegal; to kill yourself deliberately", "sentence": "They committed themselves to finishing the project together.", "sentence_trans": "\u4ed6\u4eec\u627f\u8bfa\u5171\u540c\u5b8c\u6210\u8fd9\u4e2a\u9879\u76ee\u3002", "sentence_phrase": "", "word_etyma": "com\u4e00\u8d77 + mit\u91ca\u653e\uff0c\u629b\u51fa \u2192 \u67d0\u79cd\u884c\u4e3a\u7684\u5ba3\u6cc4 \u2192 commit\u627f\u8bfa\uff0c\u81ea\u6740"}