{"word": "finger", "accent": "/\u02c8f\u026a\u014b\u0261\u0259r/", "mean_cn": "n.\u624b\u6307\uff1b  v.\u89e6\u78b0\uff0c\u7528\u6307\u629a\u6478", "mean_en": "one of the four that are not the thumb", "sentence": "He showed me three fingers.", "sentence_trans": "\u4ed6\u671d\u6211\u6bd4\u51fa\u4e86\u4e09\u6839\u624b\u6307\u3002", "sentence_phrase": "", "word_etyma": "fing\u4e94 + er\u540d\u8bcd\u540e\u7f00\uff0c\u4eba\u6216\u7269 \u2192 \u4eba\u6709\u4e94\u4e2a\u624b\u6307 \u2192 finger\u624b\u6307"}