{"word": "immigrant", "accent": "/\u02c8\u026am\u026a\u0261r\u0259nt/ ", "mean_cn": "n.\u79fb\u6c11\uff0c\u5916\u4fa8", "mean_en": "a person who has come to live permanently in a country that is not their own", "sentence": "Immigrants bring cultural diversity.", "sentence_trans": "\u79fb\u6c11\u5e26\u6765\u4e86\u6587\u5316\u591a\u6837\u6027\u3002", "sentence_phrase": "", "word_etyma": "im\u5411\u5185\uff0c\u8fdb\u5165 + migr\u8fc1\u79fb + ant\u8868\u793a\u4eba\uff1b\u5f62\u5bb9\u8bcd \u2192 immigrant\u5916\u6765\u7684\u79fb\u6c11\uff1b\u79fb\u5165\u56fd\u5185\u7684"}