{"word": "materialism", "accent": "/m\u0259\u02c8t\u026ari\u0259l\u026az\u0259m/", "mean_cn": "n.\u552f\u7269\u4e3b\u4e49\uff0c\u7269\u8d28\u4e3b\u4e49", "mean_en": "the belief that money, possessions and physical comforts are more important than spiritual values; the belief that only material things exist", "sentence": "Marx is famous for his ideas on materialism.", "sentence_trans": "\u9a6c\u514b\u601d\u4ee5\u5176\u5173\u4e8e\u552f\u7269\u4e3b\u4e49\u7684\u89c2\u70b9\u800c\u95fb\u540d\u3002", "sentence_phrase": "", "word_etyma": "material\u7269\u8d28 + ism\u4e3b\u4e49 \u2192 materialism\u552f\u7269\u4e3b\u4e49"}