{"word": "obscene", "accent": "/\u0259b\u02c8si\u02d0n/", "mean_cn": "adj.\u4e0b\u6d41\u7684\uff0c\u6deb\u79fd\u7684", "mean_en": "connected with sex in a way that most people find offensive; extremely large in size or amount in a way that most people find unacceptable and offensive", "sentence": "This person's obscene gesture annoyed the other person. ", "sentence_trans": "\u8fd9\u4e2a\u4eba\u4e0b\u6d41\u7684\u624b\u52bf\u8ba9\u5bf9\u65b9\u611f\u5230\u607c\u706b\u3002", "sentence_phrase": "", "word_etyma": ""}