{"word": "sophisticated", "accent": "/s\u0259\u02c8f\u026ast\u026ake\u026at\u026ad/", "mean_cn": "adj.\u7cbe\u5bc6\u7684\uff1b\u8001\u7ec3\u7684", "mean_en": "having a lot of experience of the world and knowing about fashion, culture and other things that people think are socially important", "sentence": "This machine is quite sophisticated.", "sentence_trans": "\u8fd9\u53f0\u673a\u5668\u662f\u975e\u5e38\u7cbe\u5bc6\u7684\u3002", "sentence_phrase": "", "word_etyma": "soph\u667a\u6167 + istic\u2026\u2026\u7684 + at\uff1date\u505a\uff0c\u9020\u6210 + ed\u2026\u2026\u7684 \u2192 \u6709\u667a\u6167\u7684 \u2192 sophisticated\u8001\u4e8e\u4e16\u6545\u7684\uff0c\u7cbe\u81f4\u590d\u6742\u7684"}